wagtail_restaurant/__init__.py
wagtail_restaurant/company/__init__.py
wagtail_restaurant/company/admin.py
wagtail_restaurant/company/apps.py
wagtail_restaurant/company/blocks.py
wagtail_restaurant/company/models.py
wagtail_restaurant/company/management/__init__.py
wagtail_restaurant/company/management/commands/__init__.py
wagtail_restaurant/company/management/commands/create_opening_hours.py
wagtail_restaurant/company/migrations/0001_initial.py
wagtail_restaurant/company/migrations/__init__.py
wagtail_restaurant/company/templatetags/__init__.py
wagtail_restaurant/company/templatetags/opening_hours_tags.py
wagtail_restaurant/contact/__init__.py
wagtail_restaurant/contact/apps.py
wagtail_restaurant/contact/models.py
wagtail_restaurant/contact/management/__init__.py
wagtail_restaurant/contact/management/commands/__init__.py
wagtail_restaurant/contact/management/commands/create_contact_form.py
wagtail_restaurant/contact/management/commands/create_contact_page.py
wagtail_restaurant/contact/migrations/0001_initial.py
wagtail_restaurant/contact/migrations/__init__.py
wagtail_restaurant/core/__init__.py
wagtail_restaurant/core/apps.py
wagtail_restaurant/core/wagtail_hooks.py
wagtail_restaurant/gallery/__init__.py
wagtail_restaurant/gallery/apps.py
wagtail_restaurant/gallery/blocks.py
wagtail_restaurant/gallery/models.py
wagtail_restaurant/gallery/management/__init__.py
wagtail_restaurant/gallery/management/commands/__init__.py
wagtail_restaurant/gallery/management/commands/create_gallery_page.py
wagtail_restaurant/gallery/migrations/0001_initial.py
wagtail_restaurant/gallery/migrations/__init__.py
wagtail_restaurant/menu/__init__.py
wagtail_restaurant/menu/apps.py
wagtail_restaurant/menu/blocks.py
wagtail_restaurant/menu/models.py
wagtail_restaurant/menu/management/__init__.py
wagtail_restaurant/menu/management/commands/__init__.py
wagtail_restaurant/menu/management/commands/create_menu_page.py
wagtail_restaurant/menu/migrations/0001_initial.py
wagtail_restaurant-0.0.8.dist-info/LICENSE
wagtail_restaurant-0.0.8.dist-info/METADATA
wagtail_restaurant-0.0.8.dist-info/WHEEL
wagtail_restaurant-0.0.8.dist-info/top_level.txt
wagtail_restaurant-0.0.8.dist-info/RECORD
