Metadata-Version: 2.1
Name: wagtail-restaurant
Version: 0.0.8
Summary: Wagtail CMS packages for restaurants
Home-page: https://github.com/Zetasis/wagtail_restaurant_standart_modules
Author: ZETASIS
Author-email: usezeta@gmail.com
License: BSD
Keywords: wagtail restaurant menu,wagtail restaurant,restaurant
Platform: UNKNOWN
Classifier: License :: OSI Approved :: BSD License
Classifier: Programming Language :: Python :: 3.6
Classifier: Programming Language :: Python :: 3.7
Classifier: Programming Language :: Python :: 3.8
Classifier: Operating System :: OS Independent
Requires-Python: >=3.6
Requires-Dist: wagtail (>=2.11.3)
